utils/Detector.py
utils/Models.py
utils/Run.py
utils/Transformer.py
utils/VideoRead.py
utils/__init__.py
SocialDistance-0.1.1.dist-info/LICENSE
SocialDistance-0.1.1.dist-info/METADATA
SocialDistance-0.1.1.dist-info/WHEEL
SocialDistance-0.1.1.dist-info/top_level.txt
SocialDistance-0.1.1.dist-info/RECORD
