Metadata-Version: 2.1
Name: SocialDistance
Version: 0.1.1
Summary: lightweight video detection
Home-page: https://github.com/thomascong121/SocialDistance
Author: SocialDistance model contributors
Author-email: thomascong@outlook.com
License: MIT
Platform: UNKNOWN
